LICENSE
MANIFEST.in
README.md
cgl_wrapper.c
pyproject.toml
setup.py
./cgl_wrapper.pyx
cgl_py.egg-info/PKG-INFO
cgl_py.egg-info/SOURCES.txt
cgl_py.egg-info/dependency_links.txt
cgl_py.egg-info/requires.txt
cgl_py.egg-info/top_level.txt
include/cgl.h
include/freetype/builds/amiga/include/config/ftconfig.h
include/freetype/builds/amiga/include/config/ftmodule.h
include/freetype/builds/atari/ATARI.H
include/freetype/builds/vms/ftconfig.h
include/freetype/devel/ft2build.h
include/freetype/devel/ftoption.h
include/freetype/include/ft2build.h
include/freetype/include/dlg/dlg.h
include/freetype/include/dlg/output.h
include/freetype/include/freetype/freetype.h
include/freetype/include/freetype/ftadvanc.h
include/freetype/include/freetype/ftbbox.h
include/freetype/include/freetype/ftbdf.h
include/freetype/include/freetype/ftbitmap.h
include/freetype/include/freetype/ftbzip2.h
include/freetype/include/freetype/ftcache.h
include/freetype/include/freetype/ftchapters.h
include/freetype/include/freetype/ftcid.h
include/freetype/include/freetype/ftcolor.h
include/freetype/include/freetype/ftdriver.h
include/freetype/include/freetype/fterrdef.h
include/freetype/include/freetype/fterrors.h
include/freetype/include/freetype/ftfntfmt.h
include/freetype/include/freetype/ftgasp.h
include/freetype/include/freetype/ftglyph.h
include/freetype/include/freetype/ftgxval.h
include/freetype/include/freetype/ftgzip.h
include/freetype/include/freetype/ftimage.h
include/freetype/include/freetype/ftincrem.h
include/freetype/include/freetype/ftlcdfil.h
include/freetype/include/freetype/ftlist.h
include/freetype/include/freetype/ftlogging.h
include/freetype/include/freetype/ftlzw.h
include/freetype/include/freetype/ftmac.h
include/freetype/include/freetype/ftmm.h
include/freetype/include/freetype/ftmodapi.h
include/freetype/include/freetype/ftmoderr.h
include/freetype/include/freetype/ftotval.h
include/freetype/include/freetype/ftoutln.h
include/freetype/include/freetype/ftparams.h
include/freetype/include/freetype/ftpfr.h
include/freetype/include/freetype/ftrender.h
include/freetype/include/freetype/ftsizes.h
