Metadata-Version: 2.1
Name: cgl-py
Version: 0.0.11
Summary: A Python Wrapper for CGL
Home-page: https://github.com/Jaysmito101/cgl
Author: Jaysmito Mukherjee
Author-email: jaysmito101@gmail.com
License: MIT
Project-URL: Documentation, https://www.libcgl.tech/
Project-URL: Issue tracker, https://github.com/Jaysmito101/cgl/issues
Classifier: Development Status :: 3 - Alpha
Classifier: License :: OSI Approved :: MIT License
Classifier: Intended Audience :: Developers
Classifier: Natural Language :: English
Classifier: Operating System :: OS Independent
Classifier: Programming Language :: Python :: 3.6
Classifier: Programming Language :: Python :: 3.8
Classifier: Programming Language :: Python :: 3.9
Classifier: Programming Language :: Python :: 3.10
Classifier: Topic :: Office/Business :: Financial
Classifier: Topic :: Software Development :: Libraries
Classifier: Topic :: Software Development :: Libraries :: Python Modules
Classifier: Topic :: Utilities
Classifier: Typing :: Typed
Requires-Python: >=3.6.0
License-File: LICENSE
